LICENSE
MANIFEST.in
README.md
README.rst
setup.py
barc4ro/__init__.py
barc4ro/barc4ro.py
barc4ro/barc4utils.py
barc4ro/projected_thickness.py
barc4ro/version.py
barc4ro/wavefront_fitting.py
examples/__init__.py
examples/b4RO_example_01.py
examples/b4RO_example_02.py
examples/b4RO_example_03a.py
examples/b4RO_example_03b.py
oasys_barc4ro.egg-info/PKG-INFO
oasys_barc4ro.egg-info/SOURCES.txt
oasys_barc4ro.egg-info/dependency_links.txt
oasys_barc4ro.egg-info/not-zip-safe
oasys_barc4ro.egg-info/requires.txt
oasys_barc4ro.egg-info/top_level.txt