Metadata-Version: 2.1
Name: oasys-barc4ro
Version: 2024.12.20
Summary: X-ray Refractive Optics Library for Physical Optics
Home-page: https://github.com/oasys-kit/oasys-barc4ro
Download-URL: https://github.com/oasys-kit/oasys-barc4ro
Author: Rafael Celestre, Luca Rebuffi
Author-email: rafael.celestre@esrf.fr
Maintainer: Luca Rebuffi
Maintainer-email: lrebuffi@anl.gov
License: GPLv3
Keywords: dictionary,glossary,synchrotronsimulation
Classifier: Development Status :: 5 - Production/Stable
Classifier: Environment :: Console
Classifier: Environment :: Plugins
Classifier: Programming Language :: Python :: 3
Classifier: License :: OSI Approved :: GNU General Public License v3 or later (GPLv3+)
Classifier: Operating System :: POSIX
Classifier: Operating System :: Microsoft :: Windows
Classifier: Topic :: Scientific/Engineering :: Visualization
Classifier: Topic :: Software Development :: Libraries :: Python Modules
Classifier: Intended Audience :: Education
Classifier: Intended Audience :: Science/Research
Classifier: Intended Audience :: Developers
License-File: LICENSE
Requires-Dist: scipy
